baryrat.py
baryrat-2.1.1.dist-info/LICENSE
baryrat-2.1.1.dist-info/METADATA
baryrat-2.1.1.dist-info/WHEEL
baryrat-2.1.1.dist-info/top_level.txt
baryrat-2.1.1.dist-info/RECORD
