Metadata-Version: 2.2
Name: baryrat
Version: 2.1.1
Summary: A Python package for barycentric rational approximation
Home-page: https://github.com/c-f-h/baryrat
Author: Clemens Hofreither
Author-email: clemens.hofreither@ricam.oeaw.ac.at
Classifier: Programming Language :: Python :: 2.7
Classifier: Programming Language :: Python :: 3
Classifier: Intended Audience :: Science/Research
Classifier: Topic :: Scientific/Engineering :: Mathematics
Classifier: License :: OSI Approved :: BSD License
License-File: LICENSE
Requires-Dist: numpy>=1.11
Requires-Dist: scipy
Dynamic: author
Dynamic: author-email
Dynamic: classifier
Dynamic: description
Dynamic: description-content-type
Dynamic: home-page
Dynamic: requires-dist
Dynamic: summary
